{"chunk_definitions":[{"chunk_id":"cf0fpazeyk8v7","chunk_label":"unnamed-chunk-1","document_id":null,"expansion_state":0,"options":{"engine":"r","label":"unnamed-chunk-1"},"row":17,"row_count":1,"visible":true},{"chunk_id":"cmjcw2f0kgii5","chunk_label":"unnamed-chunk-3","document_id":"3336D900","expansion_state":0,"options":{"engine":"r","label":"unnamed-chunk-2"},"row":49,"row_count":1,"visible":true},{"chunk_id":"c8kfmay71tqlj","chunk_label":"unnamed-chunk-8","document_id":"3336D900","expansion_state":0,"options":{"engine":"r","label":"unnamed-chunk-3"},"row":98,"row_count":1,"visible":true},{"chunk_id":"c71s0utjzkzr0","chunk_label":"unnamed-chunk-9","document_id":"3336D900","expansion_state":0,"options":{"engine":"r","label":"unnamed-chunk-16"},"row":104,"row_count":1,"visible":true},{"chunk_id":"cizhcfm422fip","chunk_label":"unnamed-chunk-10","document_id":"3336D900","expansion_state":0,"options":{"engine":"r","label":"unnamed-chunk-10"},"row":112,"row_count":1,"visible":true}],"doc_write_time":1604617284}